wyse_mate/__init__.py
wyse_mate/client.py
wyse_mate/config.py
wyse_mate/constants.py
wyse_mate/errors.py
wyse_mate/models.py
wyse_mate/plan.py
wyse_mate/websocket.py
wyse_mate/services/__init__.py
wyse_mate/services/agent.py
wyse_mate/services/browser.py
wyse_mate/services/session.py
wyse_mate/services/team.py
wyse_mate/services/user.py
wyse_mate_sdk-0.1.2.dist-info/licenses/LICENSE
wyse_mate_sdk-0.1.2.dist-info/METADATA
wyse_mate_sdk-0.1.2.dist-info/WHEEL
wyse_mate_sdk-0.1.2.dist-info/top_level.txt
wyse_mate_sdk-0.1.2.dist-info/RECORD
