Metadata-Version: 2.4
Name: wyse-mate-sdk
Version: 0.1.2
Summary: Python SDK for Wyse Mate
Author-email: Wyse <info@wyseos.com>
License: MIT License
Project-URL: Homepage, https://github.com/WyseOS/mate-sdk-python
Project-URL: Repository, https://github.com/WyseOS/mate-sdk-python
Project-URL: Issues, https://github.com/WyseOS/mate-sdk-python/issues
Project-URL: Documentation, https://github.com/WyseOS/mate-sdk-python#readme
Project-URL: PyPI, https://pypi.org/project/wyse-mate-sdk/
Keywords: WyseOS,WyseMate,AI,Agentic Web,Mutlti Agent System
Requires-Python: >=3.9
License-File: LICENSE
Requires-Dist: requests>=2.31.0
Requires-Dist: pydantic>=2.0.0
Requires-Dist: websockets>=11.0.0
Requires-Dist: PyYAML>=6.0.0
Dynamic: license-file
